{
  "source": "الأستاذ نور الدين - الاحتمالات من الألف إلى الياء",
  "assetStrategy": "page-level source-faithful assets; tighter formula/table crops can be added later",
  "crops": [
    {
      "source": "scans/3.jpg",
      "asset": "assets/probability-page-3.jpg",
      "box": {
        "x": 0,
        "y": 0,
        "width": 860,
        "height": 1280
      },
      "caption": "صفحة المصدر 3"
    },
    {
      "source": "scans/5.jpg",
      "asset": "assets/probability-page-5.jpg",
      "box": {
        "x": 0,
        "y": 0,
        "width": 868,
        "height": 1280
      },
      "caption": "صفحة المصدر 5"
    },
    {
      "source": "scans/6.jpg",
      "asset": "assets/probability-page-6.jpg",
      "box": {
        "x": 0,
        "y": 0,
        "width": 882,
        "height": 1280
      },
      "caption": "صفحة المصدر 6"
    },
    {
      "source": "scans/7.jpg",
      "asset": "assets/probability-page-7.jpg",
      "box": {
        "x": 0,
        "y": 0,
        "width": 866,
        "height": 1280
      },
      "caption": "صفحة المصدر 7"
    },
    {
      "source": "scans/8.jpg",
      "asset": "assets/probability-page-8.jpg",
      "box": {
        "x": 0,
        "y": 0,
        "width": 885,
        "height": 1280
      },
      "caption": "صفحة المصدر 8"
    },
    {
      "source": "scans/9.jpg",
      "asset": "assets/probability-page-9.jpg",
      "box": {
        "x": 0,
        "y": 0,
        "width": 853,
        "height": 1280
      },
      "caption": "صفحة المصدر 9"
    },
    {
      "source": "scans/10.jpg",
      "asset": "assets/probability-page-10.jpg",
      "box": {
        "x": 0,
        "y": 0,
        "width": 881,
        "height": 1280
      },
      "caption": "صفحة المصدر 10"
    },
    {
      "source": "scans/11.jpg",
      "asset": "assets/probability-page-11.jpg",
      "box": {
        "x": 0,
        "y": 0,
        "width": 848,
        "height": 1280
      },
      "caption": "صفحة المصدر 11"
    },
    {
      "source": "scans/12.jpg",
      "asset": "assets/probability-page-12.jpg",
      "box": {
        "x": 0,
        "y": 0,
        "width": 900,
        "height": 1280
      },
      "caption": "صفحة المصدر 12"
    },
    {
      "source": "scans/13.jpg",
      "asset": "assets/probability-page-13.jpg",
      "box": {
        "x": 0,
        "y": 0,
        "width": 849,
        "height": 1280
      },
      "caption": "صفحة المصدر 13"
    },
    {
      "source": "scans/14.jpg",
      "asset": "assets/probability-page-14.jpg",
      "box": {
        "x": 0,
        "y": 0,
        "width": 865,
        "height": 1280
      },
      "caption": "صفحة المصدر 14"
    },
    {
      "source": "scans/15.jpg",
      "asset": "assets/probability-page-15.jpg",
      "box": {
        "x": 0,
        "y": 0,
        "width": 853,
        "height": 1280
      },
      "caption": "صفحة المصدر 15"
    },
    {
      "source": "scans/16.jpg",
      "asset": "assets/probability-page-16.jpg",
      "box": {
        "x": 0,
        "y": 0,
        "width": 886,
        "height": 1280
      },
      "caption": "صفحة المصدر 16"
    },
    {
      "source": "scans/17.jpg",
      "asset": "assets/probability-page-17.jpg",
      "box": {
        "x": 0,
        "y": 0,
        "width": 857,
        "height": 1280
      },
      "caption": "صفحة المصدر 17"
    },
    {
      "source": "scans/18.jpg",
      "asset": "assets/probability-page-18.jpg",
      "box": {
        "x": 0,
        "y": 0,
        "width": 862,
        "height": 1280
      },
      "caption": "صفحة المصدر 18"
    },
    {
      "source": "scans/19.jpg",
      "asset": "assets/probability-page-19.jpg",
      "box": {
        "x": 0,
        "y": 0,
        "width": 845,
        "height": 1280
      },
      "caption": "صفحة المصدر 19"
    },
    {
      "source": "scans/20.jpg",
      "asset": "assets/probability-page-20.jpg",
      "box": {
        "x": 0,
        "y": 0,
        "width": 882,
        "height": 1280
      },
      "caption": "صفحة المصدر 20"
    },
    {
      "source": "scans/21.jpg",
      "asset": "assets/probability-page-21.jpg",
      "box": {
        "x": 0,
        "y": 0,
        "width": 856,
        "height": 1280
      },
      "caption": "صفحة المصدر 21"
    },
    {
      "source": "scans/22.jpg",
      "asset": "assets/probability-page-22.jpg",
      "box": {
        "x": 0,
        "y": 0,
        "width": 875,
        "height": 1280
      },
      "caption": "صفحة المصدر 22"
    },
    {
      "source": "scans/23.jpg",
      "asset": "assets/probability-page-23.jpg",
      "box": {
        "x": 0,
        "y": 0,
        "width": 868,
        "height": 1280
      },
      "caption": "صفحة المصدر 23"
    },
    {
      "source": "scans/24.jpg",
      "asset": "assets/probability-page-24.jpg",
      "box": {
        "x": 0,
        "y": 0,
        "width": 885,
        "height": 1280
      },
      "caption": "صفحة المصدر 24"
    },
    {
      "source": "scans/25.jpg",
      "asset": "assets/probability-page-25.jpg",
      "box": {
        "x": 0,
        "y": 0,
        "width": 872,
        "height": 1280
      },
      "caption": "صفحة المصدر 25"
    },
    {
      "source": "scans/26.jpg",
      "asset": "assets/probability-page-26.jpg",
      "box": {
        "x": 0,
        "y": 0,
        "width": 875,
        "height": 1280
      },
      "caption": "صفحة المصدر 26"
    },
    {
      "source": "scans/27.jpg",
      "asset": "assets/probability-page-27.jpg",
      "box": {
        "x": 0,
        "y": 0,
        "width": 875,
        "height": 1280
      },
      "caption": "صفحة المصدر 27"
    },
    {
      "source": "scans/28.jpg",
      "asset": "assets/probability-page-28.jpg",
      "box": {
        "x": 0,
        "y": 0,
        "width": 898,
        "height": 1280
      },
      "caption": "صفحة المصدر 28"
    },
    {
      "source": "scans/29.jpg",
      "asset": "assets/probability-page-29.jpg",
      "box": {
        "x": 0,
        "y": 0,
        "width": 859,
        "height": 1280
      },
      "caption": "صفحة المصدر 29"
    },
    {
      "source": "scans/30.jpg",
      "asset": "assets/probability-page-30.jpg",
      "box": {
        "x": 0,
        "y": 0,
        "width": 885,
        "height": 1280
      },
      "caption": "صفحة المصدر 30"
    },
    {
      "source": "scans/31.jpg",
      "asset": "assets/probability-page-31.jpg",
      "box": {
        "x": 0,
        "y": 0,
        "width": 854,
        "height": 1280
      },
      "caption": "صفحة المصدر 31"
    },
    {
      "source": "scans/32.jpg",
      "asset": "assets/probability-page-32.jpg",
      "box": {
        "x": 0,
        "y": 0,
        "width": 870,
        "height": 1280
      },
      "caption": "صفحة المصدر 32"
    },
    {
      "source": "scans/33.jpg",
      "asset": "assets/probability-page-33.jpg",
      "box": {
        "x": 0,
        "y": 0,
        "width": 860,
        "height": 1280
      },
      "caption": "صفحة المصدر 33"
    },
    {
      "source": "scans/34.jpg",
      "asset": "assets/probability-page-34.jpg",
      "box": {
        "x": 0,
        "y": 0,
        "width": 879,
        "height": 1280
      },
      "caption": "صفحة المصدر 34"
    },
    {
      "source": "scans/35.jpg",
      "asset": "assets/probability-page-35.jpg",
      "box": {
        "x": 0,
        "y": 0,
        "width": 843,
        "height": 1280
      },
      "caption": "صفحة المصدر 35"
    },
    {
      "source": "scans/36.jpg",
      "asset": "assets/probability-page-36.jpg",
      "box": {
        "x": 0,
        "y": 0,
        "width": 877,
        "height": 1280
      },
      "caption": "صفحة المصدر 36"
    }
  ]
}
